getignore.py
getignore-2.0.1.dist-info/LICENSE
getignore-2.0.1.dist-info/METADATA
getignore-2.0.1.dist-info/WHEEL
getignore-2.0.1.dist-info/entry_points.txt
getignore-2.0.1.dist-info/top_level.txt
getignore-2.0.1.dist-info/RECORD
