Metadata-Version: 2.1
Name: getignore
Version: 2.0.1
Summary: Command line utility to download common .gitignore files
Home-page: https://github.com/Jackevansevo/getignore
Author: Jack Evans
Author-email: jack@evans.gb.net
License: MIT
Keywords: github gitignore download
Platform: UNKNOWN
Classifier: Programming Language :: Python :: 3
Classifier: License :: OSI Approved :: MIT License
Classifier: Operating System :: OS Independent
